luminary_fpga/__init__.py
luminary_fpga/ecp5.py
luminary_fpga/ila.py
luminary_fpga/intel.py
luminary_fpga/jtag.py
luminary_fpga/onboard_jtag.py
luminary_fpga/spi.py
luminary_fpga/commands/__init__.py
luminary_fpga/commands/cli.py
luminary_fpga/protocol/__init__.py
luminary_fpga/protocol/jtag_svf.py
luminary_fpga/support/__init__.py
luminary_fpga/support/bits.py
luminary_fpga/support/selftest.py
luminary_fpga-0.0.6.dist-info/LICENSE
luminary_fpga-0.0.6.dist-info/METADATA
luminary_fpga-0.0.6.dist-info/WHEEL
luminary_fpga-0.0.6.dist-info/top_level.txt
luminary_fpga-0.0.6.dist-info/zip-safe
luminary_fpga-0.0.6.dist-info/RECORD
