Metadata-Version: 2.2
Name: luminary-fpga
Version: 0.0.6
Summary: Host tools for Luminary FPGA debug controllers
Home-page: https://github.com/shrine-maiden-heavy-industries/luminary
Author: Aki Van Ness, Rachel Mant
Author-email: aki@lethalbit.net, git@dragonmux.network
License: BSD-3-Clause
Project-URL: Documentation, https://github.com/shrine-maiden-heavy-industries/luminary
Project-URL: Source Code, https://github.com/shrine-maiden-heavy-industries/luminary
Project-URL: Bug Tracker, https://github.com/shrine-maiden-heavy-industries/luminary/issues
Classifier: Development Status :: 4 - Beta
Classifier: Intended Audience :: Developers
Classifier: Intended Audience :: Information Technology
Classifier: Intended Audience :: Science/Research
Classifier: License :: OSI Approved :: BSD License
Classifier: Operating System :: MacOS :: MacOS X
Classifier: Operating System :: Microsoft :: Windows
Classifier: Operating System :: POSIX :: Linux
Classifier: Programming Language :: Python :: 3.10
Classifier: Programming Language :: Python :: 3.11
Classifier: Programming Language :: Python :: 3.12
Classifier: Programming Language :: Python :: 3.13
Classifier: Topic :: Scientific/Engineering
Classifier: Topic :: Scientific/Engineering :: Electronic Design Automation (EDA)
Classifier: Topic :: Software Development
Classifier: Topic :: Software Development :: Embedded Systems
Classifier: Topic :: Software Development :: Libraries
Requires-Python: ~=3.10
License-File: LICENSE
Requires-Dist: setuptools
Requires-Dist: pyusb~=1.2.0
Requires-Dist: pyvcd<0.5,>=0.4.0
Provides-Extra: dev
Requires-Dist: nox; extra == "dev"
Dynamic: author
Dynamic: author-email
Dynamic: classifier
Dynamic: description
Dynamic: description-content-type
Dynamic: home-page
Dynamic: license
Dynamic: project-url
Dynamic: provides-extra
Dynamic: requires-dist
Dynamic: requires-python
Dynamic: summary
